icub_pybullet/__init__.py
icub_pybullet/pycub.py
icub_pybullet/utils.py
icub_pybullet/visualizer.py
icub_pybullet/configs/default.yaml
icub_pybullet/configs/skin_test.yaml
icub_pybullet/configs/with_ball.yaml
icub_pybullet/examples/push_the_ball_cartesian.py
icub_pybullet/examples/push_the_ball_pure_joints.py
icub_pybullet/examples/skin_test.py
icub_pybullet/iCub/full.urdf
icub_pybullet/iCub/package.xml
icub_pybullet/iCub/simple.urdf
icub_pybullet/iCub/meshes/vhacd/full_LeftIndex0_vhacd.obj
icub_pybullet/iCub/meshes/vhacd/full_LeftIndex1_vhacd.obj
icub_pybullet/iCub/meshes/vhacd/full_LeftIndex2_vhacd.obj
icub_pybullet/iCub/meshes/vhacd/full_LeftIndex3_vhacd.obj
icub_pybullet/iCub/meshes/vhacd/full_LeftLittle0_vhacd.obj
icub_pybullet/iCub/meshes/vhacd/full_LeftLittle1_vhacd.obj
icub_pybullet/iCub/meshes/vhacd/full_LeftLittle2_vhacd.obj
icub_pybullet/iCub/meshes/vhacd/full_LeftLittle3_vhacd.obj
icub_pybullet/iCub/meshes/vhacd/full_LeftMiddle0_vhacd.obj
icub_pybullet/iCub/meshes/vhacd/full_LeftMiddle1_vhacd.obj
icub_pybullet/iCub/meshes/vhacd/full_LeftMiddle2_vhacd.obj
icub_pybullet/iCub/meshes/vhacd/full_LeftMiddle3_vhacd.obj
icub_pybullet/iCub/meshes/vhacd/full_LeftRing0_vhacd.obj
icub_pybullet/iCub/meshes/vhacd/full_LeftRing1_vhacd.obj
icub_pybullet/iCub/meshes/vhacd/full_LeftRing2_vhacd.obj
icub_pybullet/iCub/meshes/vhacd/full_LeftRing3_vhacd.obj
icub_pybullet/iCub/meshes/vhacd/full_LeftThumb0_vhacd.obj
icub_pybullet/iCub/meshes/vhacd/full_LeftThumb1_vhacd.obj
icub_pybullet/iCub/meshes/vhacd/full_LeftThumb2_vhacd.obj
icub_pybullet/iCub/meshes/vhacd/full_LeftThumb3_vhacd.obj
icub_pybullet/iCub/meshes/vhacd/full_RightIndex0_vhacd.obj
icub_pybullet/iCub/meshes/vhacd/full_RightIndex1_vhacd.obj
icub_pybullet/iCub/meshes/vhacd/full_RightIndex2_vhacd.obj
icub_pybullet/iCub/meshes/vhacd/full_RightIndex3_vhacd.obj
icub_pybullet/iCub/meshes/vhacd/full_RightLittle0_vhacd.obj
icub_pybullet/iCub/meshes/vhacd/full_RightLittle1_vhacd.obj
icub_pybullet-1.2.5.dist-info/METADATA
icub_pybullet-1.2.5.dist-info/WHEEL
icub_pybullet-1.2.5.dist-info/top_level.txt
icub_pybullet-1.2.5.dist-info/RECORD
