Metadata-Version: 2.4
Name: icub_pybullet
Version: 1.2.5
Summary: pyCub - iCub in PyBullet
Home-page: https://www.lukasrustler.cz/pycub
Author: Lukas Rustler
Author-email: lukas.rustler@fel.cvut.cz
License: Creative Commons Attribution 4.0 International (CC BY 4.0)
Platform: any
Requires-Python: >=3.10, <3.13
Requires-Dist: numpy<2.0.0
Requires-Dist: open3d>=0.16.0
Requires-Dist: scipy
Requires-Dist: pybullet
Requires-Dist: roboticstoolbox-python
Requires-Dist: opencv-python
Requires-Dist: psutil
Requires-Dist: transforms3d
Requires-Dist: dash<3.0.0
Dynamic: author
Dynamic: author-email
Dynamic: description
Dynamic: description-content-type
Dynamic: home-page
Dynamic: license
Dynamic: platform
Dynamic: requires-dist
Dynamic: requires-python
Dynamic: summary
